iterpath/__init__.py
iterpath/core.py
iterpath/py.typed
iterpath/selectors.py
iterpath-0.4.1.dist-info/METADATA
iterpath-0.4.1.dist-info/WHEEL
iterpath-0.4.1.dist-info/licenses/LICENSE
iterpath-0.4.1.dist-info/RECORD
