Metadata-Version: 2.3
Name: iterpath
Version: 0.4.1
Summary: Iterate through a file tree
Project-URL: Source Code, https://github.com/jwodder/iterpath
Project-URL: Bug Tracker, https://github.com/jwodder/iterpath/issues
Author-email: John Thorvald Wodder II <iterpath@varonathe.org>
License: MIT
Keywords: DirEntry,directories,directory tree,file tree,files,find,path,pathlib,walk
Classifier: Intended Audience :: Developers
Classifier: Intended Audience :: System Administrators
Classifier: License :: OSI Approved :: MIT License
Classifier: Programming Language :: Python :: 3
Classifier: Programming Language :: Python :: 3 :: Only
Classifier: Programming Language :: Python :: 3.8
Classifier: Programming Language :: Python :: 3.9
Classifier: Programming Language :: Python :: 3.10
Classifier: Programming Language :: Python :: 3.11
Classifier: Programming Language :: Python :: 3.12
Classifier: Programming Language :: Python :: 3.13
Classifier: Programming Language :: Python :: Implementation :: CPython
Classifier: Programming Language :: Python :: Implementation :: PyPy
Classifier: Topic :: System :: Filesystems
Classifier: Typing :: Typed
Requires-Python: >=3.8
